enveloop/__init__.py
enveloop/infinite_loop.py
enveloop-0.1.0.dist-info/LICENSE
enveloop-0.1.0.dist-info/METADATA
enveloop-0.1.0.dist-info/WHEEL
enveloop-0.1.0.dist-info/entry_points.txt
enveloop-0.1.0.dist-info/top_level.txt
enveloop-0.1.0.dist-info/RECORD
