Metadata-Version: 2.1
Name: enveloop
Version: 0.1.0
Summary: Various utility for handling loops, recursions, etc.
Home-page: https://github.com/arrrlo/enveloop.git
Author: Ivan Arar
Author-email: ivan.arar@gmail.com
License: MIT
Project-URL: Source, https://github.com/arrrlo/enveloop.git
Keywords: loop,recursion,infinite-loop
Platform: UNKNOWN
Classifier: Development Status :: 4 - Beta
Classifier: Intended Audience :: Developers
Classifier: Topic :: Software Development :: Build Tools
Classifier: License :: OSI Approved :: MIT License
Classifier: Programming Language :: Python :: 3.7
Requires-Dist: click (~=7.0)
